{"0": {"id": "31f887c6ba5d418a76f63c575bc120dde6867333bfd2f10f87ad863ec16c6463", "author": "PextBot", "prerelease": true, "releases": "https://github.com/Pext/Pext/releases/tag/continuous", "assets": {}, "tag": "continuous", "published_at": "2020-08-12T08:17:32Z"}, "1": {"id": "4fb7e712c50bccc42588cdddb218734b8abcbd38154b935a8e356bd2d3223c38", "author": "TheLastProject", "prerelease": false, "releases": "https://github.com/Pext/Pext/releases/tag/v0.31", "assets": {"bad8915260184c909b43afd422569d86": {"name": "Pext-0.31-x86_64.AppImage", "download": "https://github.com/Pext/Pext/releases/download/v0.31/Pext-0.31-x86_64.AppImage", "count": 20, "size": "102.37 MB"}, "48e4abe6ee34424e86a8672d5fd63d19": {"name": "Pext-portable-0.31-x86_64.AppImage", "download": "https://github.com/Pext/Pext/releases/download/v0.31/Pext-portable-0.31-x86_64.AppImage", "count": 5, "size": "102.37 MB"}}, "tag": "v0.31", "published_at": "2020-06-21T14:03:41Z"}, "2": {"id": "e47040b84b0ebb2ba693aff64d11046bb7a65430795cc8b32da9232679b8aa5d", "author": "TheLastProject", "prerelease": false, "releases": "https://github.com/Pext/Pext/releases/tag/v0.30", "assets": {"c993e250e0c940dfa63106ef9c19242c": {"name": "Pext-0.30-x86_64.AppImage", "download": "https://github.com/Pext/Pext/releases/download/v0.30/Pext-0.30-x86_64.AppImage", "count": 23, "size": "89.85 MB"}, "d2b4e57532e049589b6c13d6c3e792e4": {"name": "Pext-portable-0.30-x86_64.AppImage", "download": "https://github.com/Pext/Pext/releases/download/v0.30/Pext-portable-0.30-x86_64.AppImage", "count": 4, "size": "89.85 MB"}}, "tag": "v0.30", "published_at": "2020-04-17T19:21:43Z"}, "3": {"id": "e6eeeb38f8bdad5535cfa76edd68f32ba84ece6c956b86ddbcc4981c71225862", "author": "TheLastProject", "prerelease": false, "releases": "https://github.com/Pext/Pext/releases/tag/v0.29", "assets": {"39eced7a43f2438aa5afef7739684be8": {"name": "Pext-0.29-x86_64.AppImage", "download": "https://github.com/Pext/Pext/releases/download/v0.29/Pext-0.29-x86_64.AppImage", "count": 49, "size": "88.90 MB"}, "82188152aee44b93afcf41d7c3f66048": {"name": "Pext-portable-0.29-x86_64.AppImage", "download": "https://github.com/Pext/Pext/releases/download/v0.29/Pext-portable-0.29-x86_64.AppImage", "count": 5, "size": "88.90 MB"}}, "tag": "v0.29", "published_at": "2020-03-07T20:08:46Z"}, "4": {"id": "6e1a5c926e004bba674f037382a79b1d80a410c8f92a066ff42c80ba11111a01", "author": "TheLastProject", "prerelease": false, "releases": "https://github.com/Pext/Pext/releases/tag/v0.28", "assets": {"9ad3ba9f5ad54e67950e900ba178e9b9": {"name": "Pext-0.28-x86_64.AppImage", "download": "https://github.com/Pext/Pext/releases/download/v0.28/Pext-0.28-x86_64.AppImage", "count": 18, "size": "89.12 MB"}, "e670b75b8d2f408ea097e0f52e0af8d0": {"name": "Pext-portable-0.28-x86_64.AppImage", "download": "https://github.com/Pext/Pext/releases/download/v0.28/Pext-portable-0.28-x86_64.AppImage", "count": 6, "size": "89.12 MB"}}, "tag": "v0.28", "published_at": "2020-01-18T19:46:56Z"}, "5": {"id": "94dc6729d8b725c26b33ab95e4be2b57df34c5da4717c3d8271cd4d5f5c064d9", "author": "TheLastProject", "prerelease": false, "releases": "https://github.com/Pext/Pext/releases/tag/v0.27", "assets": {"d28651fe7a0e410b81390f7d8e743669": {"name": "Pext-0.27-x86_64.AppImage", "download": "https://github.com/Pext/Pext/releases/download/v0.27/Pext-0.27-x86_64.AppImage", "count": 16, "size": "88.12 MB"}, "7aa4488389f24f6881f3d349d2d74957": {"name": "Pext-portable-0.27-x86_64.AppImage", "download": "https://github.com/Pext/Pext/releases/download/v0.27/Pext-portable-0.27-x86_64.AppImage", "count": 6, "size": "88.12 MB"}}, "tag": "v0.27", "published_at": "2019-11-15T21:05:11Z"}, "6": {"id": "39793dc81905bb9a72c427a3b6204734964cdbf6153d65258c42482427fa8153", "author": "TheLastProject", "prerelease": false, "releases": "https://github.com/Pext/Pext/releases/tag/v0.26", "assets": {"729acef77a8a4cabb80a14b5ae61a6eb": {"name": "Pext-0.26-x86_64.AppImage", "download": "https://github.com/Pext/Pext/releases/download/v0.26/Pext-0.26-x86_64.AppImage", "count": 29, "size": "86.49 MB"}, "9e8c8e753187405a915205bfa72d751e": {"name": "Pext-portable-0.26-x86_64.AppImage", "download": "https://github.com/Pext/Pext/releases/download/v0.26/Pext-portable-0.26-x86_64.AppImage", "count": 7, "size": "86.49 MB"}}, "tag": "v0.26", "published_at": "2019-10-18T19:08:36Z"}, "7": {"id": "674fffa2e21b281ddba3513a69edc7eb97b79368f05a5b7ceb0e94d4fbdf91ff", "author": "TheLastProject", "prerelease": false, "releases": "https://github.com/Pext/Pext/releases/tag/v0.25", "assets": {"d34b70efd1ae47b58625070f866b5ca7": {"name": "Pext-0.25-x86_64.AppImage", "download": "https://github.com/Pext/Pext/releases/download/v0.25/Pext-0.25-x86_64.AppImage", "count": 16, "size": "89.62 MB"}, "cc0375fb46f44a56872264d9322b93c4": {"name": "Pext-portable-0.25-x86_64.AppImage", "download": "https://github.com/Pext/Pext/releases/download/v0.25/Pext-portable-0.25-x86_64.AppImage", "count": 9, "size": "89.62 MB"}}, "tag": "v0.25", "published_at": "2019-10-04T19:49:07Z"}, "8": {"id": "027711dcc9e0dfe56f5d3223039862940a6508275adbe573719abd5442f8c6c6", "author": "TheLastProject", "prerelease": false, "releases": "https://github.com/Pext/Pext/releases/tag/v0.24.1", "assets": {"9960328fda3546298e7eafb2d1ab7b1f": {"name": "Pext-0.24.1-x86_64.AppImage", "download": "https://github.com/Pext/Pext/releases/download/v0.24.1/Pext-0.24.1-x86_64.AppImage", "count": 28, "size": "88.78 MB"}, "54ba78e3bca041f79f726fb410c1374e": {"name": "Pext-portable-0.24.1-x86_64.AppImage", "download": "https://github.com/Pext/Pext/releases/download/v0.24.1/Pext-portable-0.24.1-x86_64.AppImage", "count": 5, "size": "88.78 MB"}}, "tag": "v0.24.1", "published_at": "2019-09-08T13:04:30Z"}, "9": {"id": "b3803b05f4b61b413bb1aa38e27b423ffefa4d1530b79faa6bef9daf19a01316", "author": "TheLastProject", "prerelease": false, "releases": "https://github.com/Pext/Pext/releases/tag/v0.24.0", "assets": {"a2eada409428482a96b9785512b3b620": {"name": "Pext-0.24.0-x86_64.AppImage", "download": "https://github.com/Pext/Pext/releases/download/v0.24.0/Pext-0.24.0-x86_64.AppImage", "count": 35, "size": "102.97 MB"}, "1e6a5325e3314cfd8fe9065b3099a056": {"name": "Pext-portable-0.24.0-x86_64.AppImage", "download": "https://github.com/Pext/Pext/releases/download/v0.24.0/Pext-portable-0.24.0-x86_64.AppImage", "count": 7, "size": "102.97 MB"}}, "tag": "v0.24.0", "published_at": "2019-06-28T18:20:41Z"}, "10": {"id": "e1ffc366431c9b0beaf327cd90b043e75779cf1842fcee7988e99d9b12990a35", "author": "TheLastProject", "prerelease": false, "releases": "https://github.com/Pext/Pext/releases/tag/v0.23", "assets": {"86bf153c3a2e4142bcaea06afb2316b2": {"name": "Pext-0.23-x86_64.AppImage", "download": "https://github.com/Pext/Pext/releases/download/v0.23/Pext-0.23-x86_64.AppImage", "count": 97, "size": "85.13 MB"}, "8385562f091e45e2b0b3948763f98b70": {"name": "Pext-portable-0.23-x86_64.AppImage", "download": "https://github.com/Pext/Pext/releases/download/v0.23/Pext-portable-0.23-x86_64.AppImage", "count": 4, "size": "85.13 MB"}}, "tag": "v0.23", "published_at": "2019-03-19T15:47:36Z"}, "11": {"id": "fc2390df679552276402dcfdfdb814c2357f8a5edfab957b0ffd9e6849e9fd94", "author": "TheLastProject", "prerelease": false, "releases": "https://github.com/Pext/Pext/releases/tag/v0.22", "assets": {"36528a7fb91a489295a0a17ed16deabf": {"name": "Pext-0.22-x86_64.AppImage", "download": "https://github.com/Pext/Pext/releases/download/v0.22/Pext-0.22-x86_64.AppImage", "count": 52, "size": "118.14 MB"}}, "tag": "v0.22", "published_at": "2018-12-19T19:38:14Z"}, "12": {"id": "4633c6a3112a459651e1c24d844f8254e476a1a729908ad89b75cdd6c133c12e", "author": "TheLastProject", "prerelease": false, "releases": "https://github.com/Pext/Pext/releases/tag/v0.21", "assets": {"a2f1591c9d0742388588f8b1d291a850": {"name": "Pext-0.21-x86_64.AppImage", "download": "https://github.com/Pext/Pext/releases/download/v0.21/Pext-0.21-x86_64.AppImage", "count": 27, "size": "117.96 MB"}}, "tag": "v0.21", "published_at": "2018-11-02T18:28:04Z"}, "13": {"id": "eccbfa884d43f8ed00e4e15c1a106d4d2d4a351d1e7abf2b29f80f6ec2f9d0fc", "author": "TheLastProject", "prerelease": false, "releases": "https://github.com/Pext/Pext/releases/tag/v0.20", "assets": {"1eea588911fb4fca83d3cb919f4ebc96": {"name": "Pext-0.20-x86_64.AppImage", "download": "https://github.com/Pext/Pext/releases/download/v0.20/Pext-0.20-x86_64.AppImage", "count": 24, "size": "117.81 MB"}}, "tag": "v0.20", "published_at": "2018-10-12T18:27:51Z"}, "14": {"id": "2b515aefffa3ce540c356e438b064c8221646b3f8a6a4bced0d431b42e318512", "author": "TheLastProject", "prerelease": false, "releases": "https://github.com/Pext/Pext/releases/tag/v0.19", "assets": {"f29ef0a62813477cbf78cb6d321763b4": {"name": "Pext-x86_64.AppImage", "download": "https://github.com/Pext/Pext/releases/download/v0.19/Pext-x86_64.AppImage", "count": 33, "size": "395.19 MB"}}, "tag": "v0.19", "published_at": "2018-09-05T18:44:33Z"}, "15": {"id": "89b3c31e2fde270e3e06520ec91deafffaf39f0d5efdce307b884f5273541fb5", "author": "TheLastProject", "prerelease": false, "releases": "https://github.com/Pext/Pext/releases/tag/v0.18", "assets": {"da5876475b874dcab0bf2d92a9674943": {"name": "Pext-x86_64.AppImage", "download": "https://github.com/Pext/Pext/releases/download/v0.18/Pext-x86_64.AppImage", "count": 29, "size": "264.97 MB"}}, "tag": "v0.18", "published_at": "2018-08-22T11:08:43Z"}, "16": {"id": "36706b4fa170a3b3f2362a71573d610fda8756278c1b3291f2b4de15adf425af", "author": "TheLastProject", "prerelease": false, "releases": "https://github.com/Pext/Pext/releases/tag/v0.17", "assets": {"49be5b54a3ab4cab8425fb656811d1dd": {"name": "Pext-x86_64.AppImage", "download": "https://github.com/Pext/Pext/releases/download/v0.17/Pext-x86_64.AppImage", "count": 21, "size": "264.12 MB"}}, "tag": "v0.17", "published_at": "2018-07-08T14:31:40Z"}, "17": {"id": "b3c32175c56541f60b80759c6d3dcad06f094823cabcb52245807b35c60e08a8", "author": "TheLastProject", "prerelease": false, "releases": "https://github.com/Pext/Pext/releases/tag/v0.16", "assets": {"003ce3e5b70f479689cededf07680114": {"name": "Pext-x86_64.AppImage", "download": "https://github.com/Pext/Pext/releases/download/v0.16/Pext-x86_64.AppImage", "count": 18, "size": "250.73 MB"}}, "tag": "v0.16", "published_at": "2018-06-22T18:08:02Z"}, "18": {"id": "916ba715f8741445e5ccebb27da2bc05415bb5eb425e3c62818722086dee93c3", "author": "TheLastProject", "prerelease": false, "releases": "https://github.com/Pext/Pext/releases/tag/v0.15", "assets": {"77b0200546bf4ada850ae79b50d17651": {"name": "Pext-x86_64.AppImage", "download": "https://github.com/Pext/Pext/releases/download/v0.15/Pext-x86_64.AppImage", "count": 17, "size": "249.83 MB"}}, "tag": "v0.15", "published_at": "2018-06-07T08:17:22Z"}, "19": {"id": "4fca79f04b3c32aee6bbad7eae97fa07f03f50cbcc3fd1e59bbb6feb4cf269f8", "author": "TheLastProject", "prerelease": false, "releases": "https://github.com/Pext/Pext/releases/tag/v0.14", "assets": {"41dce498a04d4ad5a5f9cdfd96ae422f": {"name": "Pext-x86_64.AppImage", "download": "https://github.com/Pext/Pext/releases/download/v0.14/Pext-x86_64.AppImage", "count": 13, "size": "218.95 MB"}}, "tag": "v0.14", "published_at": "2018-04-22T11:18:56Z"}, "20": {"id": "79a1e551656e3ca4b2c6ab42396ab70527754bac071ed88b9459e766e5ae903a", "author": "TheLastProject", "prerelease": false, "releases": "https://github.com/Pext/Pext/releases/tag/v0.13", "assets": {"d4827e9716944c909dad4b6cdca2c295": {"name": "Pext-x86_64.AppImage", "download": "https://github.com/Pext/Pext/releases/download/v0.13/Pext-x86_64.AppImage", "count": 25, "size": "218.94 MB"}}, "tag": "v0.13", "published_at": "2018-04-07T10:50:50Z"}, "21": {"id": "31f887c6ba5d418a76f63c575bc120dde6867333bfd2f10f87ad863ec16c6463", "author": "TheLastProject", "prerelease": false, "releases": "https://github.com/Pext/Pext/releases/tag/v0.12", "assets": {}, "tag": "v0.12", "published_at": "2018-03-04T17:42:18Z"}, "22": {"id": "31f887c6ba5d418a76f63c575bc120dde6867333bfd2f10f87ad863ec16c6463", "author": "TheLastProject", "prerelease": false, "releases": "https://github.com/Pext/Pext/releases/tag/v0.11.1", "assets": {}, "tag": "v0.11.1", "published_at": "2017-12-19T17:48:25Z"}, "23": {"id": "31f887c6ba5d418a76f63c575bc120dde6867333bfd2f10f87ad863ec16c6463", "author": "TheLastProject", "prerelease": false, "releases": "https://github.com/Pext/Pext/releases/tag/v0.11", "assets": {}, "tag": "v0.11", "published_at": "2017-12-19T17:47:56Z"}, "24": {"id": "31f887c6ba5d418a76f63c575bc120dde6867333bfd2f10f87ad863ec16c6463", "author": "TheLastProject", "prerelease": false, "releases": "https://github.com/Pext/Pext/releases/tag/v0.10", "assets": {}, "tag": "v0.10", "published_at": "2017-11-11T21:50:58Z"}, "25": {"id": "31f887c6ba5d418a76f63c575bc120dde6867333bfd2f10f87ad863ec16c6463", "author": "TheLastProject", "prerelease": false, "releases": "https://github.com/Pext/Pext/releases/tag/v0.9", "assets": {}, "tag": "v0.9", "published_at": "2017-11-06T16:29:58Z"}, "26": {"id": "31f887c6ba5d418a76f63c575bc120dde6867333bfd2f10f87ad863ec16c6463", "author": "TheLastProject", "prerelease": false, "releases": "https://github.com/Pext/Pext/releases/tag/v0.8", "assets": {}, "tag": "v0.8", "published_at": "2017-11-06T16:29:46Z"}, "27": {"id": "31f887c6ba5d418a76f63c575bc120dde6867333bfd2f10f87ad863ec16c6463", "author": "TheLastProject", "prerelease": false, "releases": "https://github.com/Pext/Pext/releases/tag/v0.7", "assets": {}, "tag": "v0.7", "published_at": "2017-04-10T18:52:35Z"}, "28": {"id": "31f887c6ba5d418a76f63c575bc120dde6867333bfd2f10f87ad863ec16c6463", "author": "TheLastProject", "prerelease": false, "releases": "https://github.com/Pext/Pext/releases/tag/v0.6.1", "assets": {}, "tag": "v0.6.1", "published_at": "2017-04-01T13:26:04Z"}, "29": {"id": "31f887c6ba5d418a76f63c575bc120dde6867333bfd2f10f87ad863ec16c6463", "author": "TheLastProject", "prerelease": false, "releases": "https://github.com/Pext/Pext/releases/tag/v0.6", "assets": {}, "tag": "v0.6", "published_at": "2017-03-27T16:11:31Z"}, "owner": "Pext", "source": {"type": "github", "url": "https://github.com/Pext/Pext"}}