{"0": {"id": "6844e17b09868da446212a0961dfea52140b1d4143992632f053aaa2d6c16198", "author": "Sn8z", "prerelease": false, "releases": "https://github.com/Sn8z/Poddr/releases/tag/2.0.0", "assets": {"2cb2c843cbc24ec8b7b3670720785120": {"name": "Poddr-2.0.0.AppImage", "download": "https://github.com/Sn8z/Poddr/releases/download/2.0.0/Poddr-2.0.0.AppImage", "count": 1110, "size": "90.74 MB"}}, "tag": "2.0.0", "published_at": "2019-11-12T19:12:31Z"}, "1": {"id": "8152924bd4ab6cb4073f8b8cbdc9949416fc4cf46ba2e2eb9345865a848d75dd", "author": "Sn8z", "prerelease": false, "releases": "https://github.com/Sn8z/Poddr/releases/tag/v1.1.0", "assets": {"9c18bf98c8034f748c9652762ce47b4b": {"name": "Poddr.1.1.0.AppImage", "download": "https://github.com/Sn8z/Poddr/releases/download/v1.1.0/Poddr.1.1.0.AppImage", "count": 1289, "size": "83.92 MB"}}, "tag": "v1.1.0", "published_at": "2019-03-04T14:53:12Z"}, "2": {"id": "ab647d9aa6c1f8185ae8660808570b1069604d5f1bb98871d557fad03749f6df", "author": "Sn8z", "prerelease": false, "releases": "https://github.com/Sn8z/Poddr/releases/tag/v1.0.9", "assets": {"d509b881f48444bc84b7aed83e5028d2": {"name": "poddr-1.0.9-x86_64.AppImage", "download": "https://github.com/Sn8z/Poddr/releases/download/v1.0.9/poddr-1.0.9-x86_64.AppImage", "count": 493, "size": "59.50 MB"}}, "tag": "v1.0.9", "published_at": "2018-11-08T21:00:56Z"}, "3": {"id": "117e4c0a06ee03d73bc3f7744144a649005310a4b3bf0d1b6b4b45f4d111ccc8", "author": "Sn8z", "prerelease": false, "releases": "https://github.com/Sn8z/Poddr/releases/tag/v1.0.8", "assets": {"68cc75611c794bc6878cf877614839ef": {"name": "poddr-1.0.8-x86_64.AppImage", "download": "https://github.com/Sn8z/Poddr/releases/download/v1.0.8/poddr-1.0.8-x86_64.AppImage", "count": 104, "size": "56.75 MB"}}, "tag": "v1.0.8", "published_at": "2018-09-27T12:19:26Z"}, "4": {"id": "bc41ba39fdfc952cc214c18e2ce2392c5238a5e4713fd6b56b2d2c8b24ed4170", "author": "Sn8z", "prerelease": false, "releases": "https://github.com/Sn8z/Poddr/releases/tag/v1.0.7", "assets": {"10ca6e1ac2994abe99f038ac27be9e21": {"name": "poddr-1.0.7-x86_64.AppImage", "download": "https://github.com/Sn8z/Poddr/releases/download/v1.0.7/poddr-1.0.7-x86_64.AppImage", "count": 46, "size": "54.60 MB"}}, "tag": "v1.0.7", "published_at": "2018-06-20T08:28:48Z"}, "5": {"id": "fa7a0693d229b840558003dc4247ed27e3161641efad4c8297c08e8bae634027", "author": "Sn8z", "prerelease": false, "releases": "https://github.com/Sn8z/Poddr/releases/tag/1.0.6", "assets": {"c88efa3cbe7c474186cd076ac4aad5ba": {"name": "poddr-1.0.6-x86_64.AppImage", "download": "https://github.com/Sn8z/Poddr/releases/download/1.0.6/poddr-1.0.6-x86_64.AppImage", "count": 58, "size": "65.36 MB"}}, "tag": "1.0.6", "published_at": "2018-03-15T09:03:27Z"}, "6": {"id": "d13c912fbb472e64a2fba42ad0d3ddff852e4b5d75685970964d9b26bf305f35", "author": "Sn8z", "prerelease": false, "releases": "https://github.com/Sn8z/Poddr/releases/tag/1.0.5", "assets": {"51517ee7ee2941c09a8b2b650a205132": {"name": "poddr-1.0.5-x86_64.AppImage", "download": "https://github.com/Sn8z/Poddr/releases/download/1.0.5/poddr-1.0.5-x86_64.AppImage", "count": 51, "size": "59.20 MB"}}, "tag": "1.0.5", "published_at": "2018-02-13T08:12:37Z"}, "7": {"id": "461cabda8b5b41df392447aefd588cffb463d7586d85bd0152db7e03228cf2ad", "author": "Sn8z", "prerelease": false, "releases": "https://github.com/Sn8z/Poddr/releases/tag/1.0.3", "assets": {}, "tag": "1.0.3", "published_at": "2017-09-23T10:26:58Z"}, "owner": "Sn8z", "source": {"type": "github", "url": "https://github.com/Sn8z/Poddr"}}