{"0": {"id": "27a0f1f35156ec3ff6a65613535d60dc525f16ad2afcc8b5f713b114df68afc2", "author": "aenany", "prerelease": false, "releases": "https://github.com/aenany/snake.js/releases/tag/v0.0.2", "assets": {"c7a674dbb2c343208fd03afd019e6bf3": {"name": "snake.js-0.0.2.AppImage", "download": "https://github.com/aenany/snake.js/releases/download/v0.0.2/snake.js-0.0.2.AppImage", "count": 425, "size": "67.60 MB"}}, "tag": "v0.0.2", "published_at": "2020-01-11T05:59:20Z"}, "1": {"id": "63c46beab8a4b7521d1a9d8eb6496e7c9c40908a6cf4895ac36981c9f44d7ed1", "author": "aenany", "prerelease": false, "releases": "https://github.com/aenany/snake.js/releases/tag/v0.0.1", "assets": {"b1bebc863fae4032b4a2c764544001ff": {"name": "snake.js-0.0.1-x86_64.AppImage", "download": "https://github.com/aenany/snake.js/releases/download/v0.0.1/snake.js-0.0.1-x86_64.AppImage", "count": 952, "size": "55.75 MB"}}, "tag": "v0.0.1", "published_at": "2017-12-31T22:23:50Z"}, "owner": "aenany", "source": {"type": "github", "url": "https://github.com/aenany/snake.js"}}