{"0": {"id": "7ebf1a1357af42a348a5baf58abc9c64b63711b872fef9fa6a6626d39568dadb", "author": "jgaa", "prerelease": true, "releases": "https://github.com/jgaa/f-crm/releases/tag/v0.2.0-beta", "assets": {"53bc02888f86423cba5817057ceef041": {"name": "f-crm-x86_64-0.2.0.AppImage", "download": "https://github.com/jgaa/f-crm/releases/download/v0.2.0-beta/f-crm-x86_64-0.2.0.AppImage", "count": 1275, "size": "25.20 MB"}}, "tag": "v0.2.0-beta", "published_at": "2019-01-22T07:12:49Z"}, "owner": "jgaa", "source": {"type": "github", "url": "https://github.com/jgaa/f-crm"}}