{"0": {"id": "ef13155b640a841d69d022243573f10e3dd911316ae63d05b8db4d78a51a5e9c", "author": "VinnyVynce", "prerelease": false, "releases": "https://github.com/VinnyVynce/wxMEdit.AppImage/releases/tag/3.1_FIX1", "assets": {"d36c07476ac049eaaf6a262fc48321a5": {"name": "wxMEdit-3.1_FIX1.AppImage", "download": "https://github.com/VinnyVynce/wxMEdit.AppImage/releases/download/3.1_FIX1/wxMEdit-3.1_FIX1.AppImage", "count": 50, "size": "24.45 MB"}}, "tag": "3.1_FIX1", "published_at": "2020-03-14T00:25:33Z"}, "owner": "VinnyVynce", "source": {"type": "github", "url": "https://github.com/VinnyVynce/wxMEdit.AppImage"}}