{"0": {"id": "bc1bf8734be628f4afa974587cc40e6a6bfed2fe7696ca3795b604030352f537", "author": "Zerx0r", "prerelease": false, "releases": "https://github.com/Zerx0r/Kage/releases/tag/v0.1.1-beta", "assets": {"13381df95f884e97a4250b3fbd4473cd": {"name": "Kage.0.1.1-beta_linux.AppImage", "download": "https://github.com/Zerx0r/Kage/releases/download/v0.1.1-beta/Kage.0.1.1-beta_linux.AppImage", "count": 10873, "size": "53.09 MB"}}, "tag": "v0.1.1-beta", "published_at": "2019-02-23T19:11:30Z"}, "owner": "WayzDev", "source": {"type": "github", "url": "https://github.com/WayzDev/Kage"}}