{"0": {"id": "7df0302c3c7ce0d23e3604b20b91d4e06eab5e7ce6c48042d8c3972fe7a7b292", "author": "mgechev", "prerelease": false, "releases": "https://github.com/ng-ast/ngrev/releases/tag/0.0.27", "assets": {"d7fe97b79de042be8bd41ed6f147b345": {"name": "ngrev-0.0.27-x86_64.AppImage", "download": "https://github.com/ng-ast/ngrev/releases/download/0.0.27/ngrev-0.0.27-x86_64.AppImage", "count": 1581, "size": "78.25 MB"}}, "tag": "0.0.27", "published_at": "2019-05-27T15:16:18Z"}, "1": {"id": "ebb2f89d34a05d62d9a28471b08fa4b44de4273cbbbc991910ed121dd4597c1f", "author": "mgechev", "prerelease": false, "releases": "https://github.com/ng-ast/ngrev/releases/tag/0.0.26", "assets": {"eacaf20df6584b1d8b4cea7adc80c9b3": {"name": "ngrev-0.0.26-x86_64.AppImage", "download": "https://github.com/ng-ast/ngrev/releases/download/0.0.26/ngrev-0.0.26-x86_64.AppImage", "count": 729, "size": "78.90 MB"}}, "tag": "0.0.26", "published_at": "2018-10-11T18:48:31Z"}, "2": {"id": "ebb13bd76fc1b0d4e25c180846849a32a1896f89a08ffddf3c7a393a21f538ca", "author": "mgechev", "prerelease": false, "releases": "https://github.com/ng-ast/ngrev/releases/tag/0.0.25", "assets": {"b4ff8a5d53aa4e6db5e059d7e6cb44e3": {"name": "ngrev-0.0.25-x86_64.AppImage", "download": "https://github.com/ng-ast/ngrev/releases/download/0.0.25/ngrev-0.0.25-x86_64.AppImage", "count": 29, "size": "78.90 MB"}}, "tag": "0.0.25", "published_at": "2018-10-10T22:16:43Z"}, "3": {"id": "baaf5cccfdd3c047fa09ba38da12ce2e9cfc9db9fb23bafc9b9186c35810de89", "author": "mgechev", "prerelease": false, "releases": "https://github.com/ng-ast/ngrev/releases/tag/0.0.24", "assets": {"173f0304f5844baab4f41867abc192d9": {"name": "ngrev-0.0.24-x86_64.AppImage", "download": "https://github.com/ng-ast/ngrev/releases/download/0.0.24/ngrev-0.0.24-x86_64.AppImage", "count": 25, "size": "78.90 MB"}}, "tag": "0.0.24", "published_at": "2018-10-09T20:50:42Z"}, "4": {"id": "beeedb573a7f9756f7160ba5d3b3f57fdb11834aa7f9f5cb85e7e18d91b0eda9", "author": "mgechev", "prerelease": false, "releases": "https://github.com/ng-ast/ngrev/releases/tag/0.0.23", "assets": {"52b5ebbf924f42bfb28cf5243d0e2f97": {"name": "ngrev-0.0.23-x86_64.AppImage", "download": "https://github.com/ng-ast/ngrev/releases/download/0.0.23/ngrev-0.0.23-x86_64.AppImage", "count": 20, "size": "78.90 MB"}}, "tag": "0.0.23", "published_at": "2018-10-08T17:51:52Z"}, "5": {"id": "0b4efc3dff1def8add03a9bfc1ce96b68f21220ede08ae3ac715b1f37f8b61ff", "author": "mgechev", "prerelease": false, "releases": "https://github.com/ng-ast/ngrev/releases/tag/0.0.22", "assets": {"6d5edf2058384e1f90a0d91a0051dcc0": {"name": "ngrev-0.0.22-x86_64.AppImage", "download": "https://github.com/ng-ast/ngrev/releases/download/0.0.22/ngrev-0.0.22-x86_64.AppImage", "count": 39, "size": "78.90 MB"}}, "tag": "0.0.22", "published_at": "2018-10-05T23:05:09Z"}, "6": {"id": "be05b8fc72542c8151667a31a0908cd9997778202b2508e000bc5b52fcb6c03c", "author": "mgechev", "prerelease": false, "releases": "https://github.com/ng-ast/ngrev/releases/tag/0.0.21", "assets": {"b43fd39ccbd548aaa0c4b8431eb4d56a": {"name": "ngrev-0.0.21-x86_64.AppImage", "download": "https://github.com/ng-ast/ngrev/releases/download/0.0.21/ngrev-0.0.21-x86_64.AppImage", "count": 257, "size": "69.13 MB"}}, "tag": "0.0.21", "published_at": "2018-04-27T17:51:27Z"}, "7": {"id": "9c3e5db52abaf5db5c086ac6b8f977ac8d310a948a54faaa08d3fced05ae88f8", "author": "mgechev", "prerelease": false, "releases": "https://github.com/ng-ast/ngrev/releases/tag/0.0.20", "assets": {"afb4fc46d0c04c89b3ce840eddcf6347": {"name": "ngrev-0.0.20-x86_64.AppImage", "download": "https://github.com/ng-ast/ngrev/releases/download/0.0.20/ngrev-0.0.20-x86_64.AppImage", "count": 29, "size": "69.16 MB"}}, "tag": "0.0.20", "published_at": "2018-04-24T05:24:34Z"}, "8": {"id": "8d8d0ec4481884c01da290617e136a3309c5b35048547dcf69e70584885861cf", "author": "mgechev", "prerelease": false, "releases": "https://github.com/ng-ast/ngrev/releases/tag/0.0.19", "assets": {"6e0ce60fc8ed4dba933e80ea6523ecda": {"name": "ngrev-0.0.19-x86_64.AppImage", "download": "https://github.com/ng-ast/ngrev/releases/download/0.0.19/ngrev-0.0.19-x86_64.AppImage", "count": 54, "size": "69.16 MB"}}, "tag": "0.0.19", "published_at": "2018-04-16T23:49:36Z"}, "9": {"id": "dca0837c51de04305b8d6a828ecae043270f87e75ca0243dbed402d5f1d09fd6", "author": "mgechev", "prerelease": false, "releases": "https://github.com/ng-ast/ngrev/releases/tag/0.0.18", "assets": {"98f8a2cc6d654f42ad4869ad81288e2e": {"name": "ngrev-0.0.18-x86_64.AppImage", "download": "https://github.com/ng-ast/ngrev/releases/download/0.0.18/ngrev-0.0.18-x86_64.AppImage", "count": 36, "size": "73.24 MB"}}, "tag": "0.0.18", "published_at": "2018-04-11T15:48:52Z"}, "10": {"id": "caccbef4e3a867c1ae05cc79cd2647cff196f7580ead97a11e7e900d52bcd875", "author": "mgechev", "prerelease": false, "releases": "https://github.com/ng-ast/ngrev/releases/tag/0.0.17", "assets": {"113d879b5a1a4ba8a8a8e29be8383add": {"name": "ngrev-0.0.17-x86_64.AppImage", "download": "https://github.com/ng-ast/ngrev/releases/download/0.0.17/ngrev-0.0.17-x86_64.AppImage", "count": 297, "size": "68.13 MB"}}, "tag": "0.0.17", "published_at": "2018-01-23T06:18:56Z"}, "11": {"id": "5a24388096b05cfbfdacd4a51b54d2a1426e65b90dfb313e36ecb148b15cf862", "author": "mgechev", "prerelease": false, "releases": "https://github.com/ng-ast/ngrev/releases/tag/0.0.16", "assets": {"0bf1994a5712410191e1c6ac82276476": {"name": "ngrev-0.0.16-x86_64.AppImage", "download": "https://github.com/ng-ast/ngrev/releases/download/0.0.16/ngrev-0.0.16-x86_64.AppImage", "count": 59, "size": "68.14 MB"}}, "tag": "0.0.16", "published_at": "2017-12-29T18:08:28Z"}, "12": {"id": "822af6d6358e2549f4413324037bf1a14aca1cb28f9fdfffa9df78b7384e3bfe", "author": "mgechev", "prerelease": false, "releases": "https://github.com/ng-ast/ngrev/releases/tag/0.0.15", "assets": {"61abde045f0f4174b307d761c9e05ec3": {"name": "ngrev-0.0.15-x86_64.AppImage", "download": "https://github.com/ng-ast/ngrev/releases/download/0.0.15/ngrev-0.0.15-x86_64.AppImage", "count": 11, "size": "68.13 MB"}}, "tag": "0.0.15", "published_at": "2017-12-28T19:27:42Z"}, "13": {"id": "bae53e4de7110654cac865d7b3128a8c8a86b95b38a1b504c370cd6eb7631836", "author": "mgechev", "prerelease": false, "releases": "https://github.com/ng-ast/ngrev/releases/tag/0.0.14", "assets": {"f5dccdda5fcd47aea1b1e473197f4cba": {"name": "ngrev-0.0.14-x86_64.AppImage", "download": "https://github.com/ng-ast/ngrev/releases/download/0.0.14/ngrev-0.0.14-x86_64.AppImage", "count": 18, "size": "68.11 MB"}}, "tag": "0.0.14", "published_at": "2017-12-24T22:12:21Z"}, "14": {"id": "f64ae9086bb309630bd02f599a6e63e52ef1bdd37ede6d26a8da9521bf1a428c", "author": "mgechev", "prerelease": false, "releases": "https://github.com/ng-ast/ngrev/releases/tag/0.0.13", "assets": {}, "tag": "0.0.13", "published_at": "2017-12-21T17:56:44Z"}, "15": {"id": "b1a32958930ab38c45317b1e9b67cc97553ed22d4b97bdb29965cb1578df23bd", "author": "mgechev", "prerelease": false, "releases": "https://github.com/ng-ast/ngrev/releases/tag/0.0.11", "assets": {"c25a781e45b94c8eadf27e29d52f5c98": {"name": "ngrev-0.0.11-x86_64.AppImage", "download": "https://github.com/ng-ast/ngrev/releases/download/0.0.11/ngrev-0.0.11-x86_64.AppImage", "count": 284, "size": "62.19 MB"}}, "tag": "0.0.11", "published_at": "2017-05-21T21:54:38Z"}, "16": {"id": "16fba5cabeb2eb4ee47dce699390136c99d17a67337b3b17156a62d1daf135e2", "author": "mgechev", "prerelease": false, "releases": "https://github.com/ng-ast/ngrev/releases/tag/0.0.10", "assets": {"ea4509eefe3a41769b240cd3ae940477": {"name": "ngrev-0.0.10-x86_64.AppImage", "download": "https://github.com/ng-ast/ngrev/releases/download/0.0.10/ngrev-0.0.10-x86_64.AppImage", "count": 18, "size": "62.19 MB"}}, "tag": "0.0.10", "published_at": "2017-05-13T02:16:45Z"}, "17": {"id": "36fdef5b40a6d9d711fa25539beef94cd79b7623223391a190d7e0813da03b40", "author": "mgechev", "prerelease": false, "releases": "https://github.com/ng-ast/ngrev/releases/tag/0.0.9", "assets": {"ac570ded548944eeb7526b52605f9696": {"name": "ngrev-0.0.9-x86_64.AppImage", "download": "https://github.com/ng-ast/ngrev/releases/download/0.0.9/ngrev-0.0.9-x86_64.AppImage", "count": 13, "size": "62.19 MB"}}, "tag": "0.0.9", "published_at": "2017-05-10T21:38:21Z"}, "18": {"id": "fc5b9e03e56404c3051992d8bdb115ed6d2ab0f97fb392e4d70b610146be6cd7", "author": "mgechev", "prerelease": false, "releases": "https://github.com/ng-ast/ngrev/releases/tag/0.0.8", "assets": {"3b92aec7264e424b930ba714243bb6b1": {"name": "ngrev-0.0.8-x86_64.AppImage", "download": "https://github.com/ng-ast/ngrev/releases/download/0.0.8/ngrev-0.0.8-x86_64.AppImage", "count": 28, "size": "62.19 MB"}}, "tag": "0.0.8", "published_at": "2017-05-01T01:28:15Z"}, "19": {"id": "43028ca2869f1a534d61a957ec1f40b8bc025eede9f5dca28cfae560b37412ee", "author": "mgechev", "prerelease": false, "releases": "https://github.com/ng-ast/ngrev/releases/tag/0.0.7", "assets": {"f45ef3d08bd542f681e461523fdcfc6e": {"name": "ngrev-0.0.7-x86_64.AppImage", "download": "https://github.com/ng-ast/ngrev/releases/download/0.0.7/ngrev-0.0.7-x86_64.AppImage", "count": 14, "size": "62.00 MB"}}, "tag": "0.0.7", "published_at": "2017-04-27T20:21:30Z"}, "20": {"id": "b9c0edabd87a75c615fceec61f749c29d8ffa7e63ec582a75c58d24ec86dc693", "author": "mgechev", "prerelease": false, "releases": "https://github.com/ng-ast/ngrev/releases/tag/0.0.6", "assets": {"6113259f34784d48b80b6fca12359e0b": {"name": "ngrev-0.0.6-x86_64.AppImage", "download": "https://github.com/ng-ast/ngrev/releases/download/0.0.6/ngrev-0.0.6-x86_64.AppImage", "count": 19, "size": "62.00 MB"}}, "tag": "0.0.6", "published_at": "2017-04-25T17:33:41Z"}, "21": {"id": "d67e8444e653db639878810c49c5daaaf49d1afd70143742186edfbee1a0cfc9", "author": "mgechev", "prerelease": false, "releases": "https://github.com/ng-ast/ngrev/releases/tag/0.0.5", "assets": {"b8e2ea0edece411da117379fede7a37c": {"name": "ngrev-0.0.5-x86_64.AppImage", "download": "https://github.com/ng-ast/ngrev/releases/download/0.0.5/ngrev-0.0.5-x86_64.AppImage", "count": 54, "size": "61.60 MB"}}, "tag": "0.0.5", "published_at": "2017-04-11T20:01:10Z"}, "22": {"id": "522181556280491dce73a1b1864c2d14c37fb62b98283df099e3b80934b44525", "author": "mgechev", "prerelease": false, "releases": "https://github.com/ng-ast/ngrev/releases/tag/0.0.4", "assets": {"e40f91666ff04bdb95fdaa1805500698": {"name": "ngrev-0.0.4-x86_64.AppImage", "download": "https://github.com/ng-ast/ngrev/releases/download/0.0.4/ngrev-0.0.4-x86_64.AppImage", "count": 9, "size": "61.60 MB"}}, "tag": "0.0.4", "published_at": "2017-04-11T16:40:17Z"}, "23": {"id": "a198d64aa811222bcffed81bc4c2f067f24a9745de3001ad1d404ff78cf52c65", "author": "mgechev", "prerelease": false, "releases": "https://github.com/ng-ast/ngrev/releases/tag/0.0.3", "assets": {"0c53b24e1d704ef9a7b4af912a205b71": {"name": "ngrev-0.0.3-x86_64.AppImage", "download": "https://github.com/ng-ast/ngrev/releases/download/0.0.3/ngrev-0.0.3-x86_64.AppImage", "count": 36, "size": "61.60 MB"}}, "tag": "0.0.3", "published_at": "2017-04-02T05:16:50Z"}, "24": {"id": "f64ae9086bb309630bd02f599a6e63e52ef1bdd37ede6d26a8da9521bf1a428c", "author": "mgechev", "prerelease": false, "releases": "https://github.com/ng-ast/ngrev/releases/tag/0.0.2", "assets": {}, "tag": "0.0.2", "published_at": "2017-03-26T02:34:21Z"}, "25": {"id": "f64ae9086bb309630bd02f599a6e63e52ef1bdd37ede6d26a8da9521bf1a428c", "author": "mgechev", "prerelease": false, "releases": "https://github.com/ng-ast/ngrev/releases/tag/0.0.1", "assets": {}, "tag": "0.0.1", "published_at": "2017-03-16T19:31:10Z"}, "26": {"id": "f64ae9086bb309630bd02f599a6e63e52ef1bdd37ede6d26a8da9521bf1a428c", "author": "mgechev", "prerelease": false, "releases": "https://github.com/ng-ast/ngrev/releases/tag/0.0.0", "assets": {}, "tag": "0.0.0", "published_at": "2017-03-15T20:29:00Z"}, "owner": "mgechev", "source": {"type": "github", "url": "https://github.com/mgechev/ngrev"}}