{"0": {"id": "b069bbf983c2f93c88bfafe2f91bf139e2ace3d238bf1bed440633778b3017f6", "author": "b00f", "prerelease": false, "releases": "https://github.com/b00f/dana/releases/tag/v1.5", "assets": {"434dd1984f08423fa6bdf9a18ea55e5c": {"name": "Dana-x86_64.AppImage", "download": "https://github.com/b00f/dana/releases/download/v1.5/Dana-x86_64.AppImage", "count": 1408, "size": "28.06 MB"}}, "tag": "v1.5", "published_at": "2018-02-27T08:27:48Z"}, "1": {"id": "394ee5e392d61f0a4dec52331bc40255e75e458a8da6558330f2b4cde048d197", "author": "b00f", "prerelease": false, "releases": "https://github.com/b00f/dana/releases/tag/v1.3", "assets": {"a59c83407ef74087b095052e24da5f6e": {"name": "Dana-x86_64.AppImage", "download": "https://github.com/b00f/dana/releases/download/v1.3/Dana-x86_64.AppImage", "count": 32, "size": "28.06 MB"}}, "tag": "v1.3", "published_at": "2018-02-22T08:08:06Z"}, "2": {"id": "276d7b547e9db52a6cf89c57b118dbad33f59dc9bfba32cdd3a1dfe2cfabf5bd", "author": "b00f", "prerelease": false, "releases": "https://github.com/b00f/dana/releases/tag/v1.2", "assets": {"ac3dd40a628c4226ae8949fcb4feac5e": {"name": "Dana-linux.AppImage", "download": "https://github.com/b00f/dana/releases/download/v1.2/Dana-linux.AppImage", "count": 18, "size": "31.97 MB"}}, "tag": "v1.2", "published_at": "2017-12-19T19:56:53Z"}, "owner": "b00f", "source": {"type": "github", "url": "https://github.com/b00f/dana"}}